byterat/__about__.py
byterat/__init__.py
byterat/client.py
byterat/config.py
byterat/data.py
byterat/filter.py
byterat/queries.py
byterat/async_/client.py
byterat/sync/client.py
byterat-0.4.3.dist-info/METADATA
byterat-0.4.3.dist-info/WHEEL
byterat-0.4.3.dist-info/licenses/LICENSE
byterat-0.4.3.dist-info/RECORD
