Metadata-Version: 2.4
Name: byterat
Version: 0.4.3
Summary: Python library to export data from and interact with the Byterat Platform
Project-URL: Platform, https://app.byterat.io
Author-email: Jayant Tandon <jayant.tandon@byterat.io>
License: Certain libraries contained in this file are subject to open source license requirements. Specifically:
License-File: LICENSE
Keywords: battery,byterat
Classifier: Development Status :: 4 - Beta
Classifier: Programming Language :: Python
Classifier: Programming Language :: Python :: 3.8
Classifier: Programming Language :: Python :: 3.9
Classifier: Programming Language :: Python :: 3.10
Classifier: Programming Language :: Python :: 3.11
Classifier: Programming Language :: Python :: 3.12
Classifier: Programming Language :: Python :: Implementation :: CPython
Classifier: Programming Language :: Python :: Implementation :: PyPy
Requires-Python: >=3.8
Requires-Dist: asyncio
Requires-Dist: gql[aiohttp,requests]
Requires-Dist: pandas
